NightWind3DLib4/Actor.py
NightWind3DLib4/__init__.py
NightWind3DLib4/actor.egg
NightWind3DLib4/actor_down.egg
NightWind3DLib4/actor_jump.egg
NightWind3DLib4/ground.egg
NightWind3DLib4/roadblock111_up.egg
NightWind3DLib4/roadblock111_updown.egg
NightWind3DLib4/roadblock121_down.egg
NightWind3DLib4/roadblock121_forbidden.egg
NightWind3DLib4/roadblock211_up.egg
NightWind3DLib4/run.py
NightWind3DLib4/__pycache__/Actor.cpython-39.pyc
NightWind3DLib4/__pycache__/__init__.cpython-39.pyc
NightWind3DLib4/__pycache__/run.cpython-39.pyc
NightWind3DLib4/tex/blackboard.png
NightWind3DLib4/tex/blackboard1.png
NightWind3DLib4/tex/bnds.jpg
NightWind3DLib4/tex/chunhong.jpg
NightWind3DLib4/tex/chunhuang.png
NightWind3DLib4/tex/chunshenlv.png
NightWind3DLib4/tex/concrete_black.png
NightWind3DLib4/tex/concrete_gray.png
NightWind3DLib4/tex/concrete_white.png
NightWind3DLib4/tex/glass_white.png
NightWind3DLib4/tex/gold.jpg
NightWind3DLib4/tex/h z.jpg
NightWind3DLib4/tex/huaban.jpg
NightWind3DLib4/tex/iron2.jpg
NightWind3DLib4/tex/j js 2.jpg
NightWind3DLib4/tex/luzhang.jpg
NightWind3DLib4/tex/paodaochunse.jpg
NightWind3DLib4/tex/paodaoshangmian.jpg
NightWind3DLib4/tex/plastic.jpg
NightWind3DLib4/tex/playground.jpg
NightWind3DLib4/tex/qy js.jpg
NightWind3DLib4/tex/redpaper.jpg
NightWind3DLib4/tex/roadblock1.jpg
NightWind3DLib4/tex/rouse.jpg
NightWind3DLib4/tex/sanhangpaodao.jpg
NightWind3DLib4/tex/shenlvgg.png
NightWind3DLib4/tex/shensemutou.png
NightWind3DLib4/tex/suliao.jpg
NightWind3DLib4/tex/threeplaygrounds.jpg
NightWind3DLib4/tex/wood2.png
NightWind3DLib4/tex/wool_colored_gray.png
NightWind3DLib4/tex/xiaofulan.jpg
NightWind3DLib4-1.0.0.dist-info/METADATA
NightWind3DLib4-1.0.0.dist-info/WHEEL
NightWind3DLib4-1.0.0.dist-info/top_level.txt
NightWind3DLib4-1.0.0.dist-info/RECORD
